<?xml version="1.0"?>

<PropertyList>
	<path>vacmeter2.ac</path>
	<texture-path>../.</texture-path>
	<offsets>
		<x-m>-2.80774</x-m>
		<y-m>0.02751</y-m>
		<z-m>0.33873</z-m>
		<pitch-deg>-8.39</pitch-deg>
	</offsets>
    <animation>
        <type>rotate</type>
        <object-name>5.Cockpit Panel Main Instruments Volt2 Needle AC</object-name>
		<property>/bell412/power/buses/bus[1]/acload</property>
        <axis>
            <x>-1</x>
            <y>0</y>
            <z>0</z>
		</axis>
  		<interpolation>
            <entry><ind>-999</ind><dep>0</dep></entry>
            <entry><ind>0</ind><dep>1</dep></entry>
            <entry><ind>90</ind><dep>5</dep></entry>
            <entry><ind>100</ind><dep>40</dep></entry>
            <entry><ind>115</ind><dep>90</dep></entry>
            <entry><ind>120</ind><dep>110</dep></entry>
            <entry><ind>130</ind><dep>145</dep></entry>
            <entry><ind>999</ind><dep>100</dep></entry>
        </interpolation>
		<condition>
			<property>bell412/power/buses/bus[1]/state</property>
		</condition>
    </animation>
</PropertyList>

